pdftools_sdk/__init__.py
pdftools_sdk/conformance_error.py
pdftools_sdk/consumption_data.py
pdftools_sdk/corrupt_error.py
pdftools_sdk/exists_error.py
pdftools_sdk/generic_error.py
pdftools_sdk/http_client_handler.py
pdftools_sdk/http_error.py
pdftools_sdk/license_error.py
pdftools_sdk/license_info.py
pdftools_sdk/metadata_dictionary.py
pdftools_sdk/not_found_error.py
pdftools_sdk/operation_error.py
pdftools_sdk/password_error.py
pdftools_sdk/permission_error.py
pdftools_sdk/processing_error.py
pdftools_sdk/retry_error.py
pdftools_sdk/sdk.py
pdftools_sdk/state_error.py
pdftools_sdk/string_list.py
pdftools_sdk/unknown_format_error.py
pdftools_sdk/unsupported_feature_error.py
pdftools_sdk/crypto/__init__.py
pdftools_sdk/crypto/hash_algorithm.py
pdftools_sdk/crypto/signature_algorithm.py
pdftools_sdk/crypto/signature_format.py
pdftools_sdk/crypto/signature_padding_type.py
pdftools_sdk/crypto/validation_information.py
pdftools_sdk/crypto/providers/__init__.py
pdftools_sdk/crypto/providers/certificate.py
pdftools_sdk/crypto/providers/certificate_list.py
pdftools_sdk/crypto/providers/provider.py
pdftools_sdk/crypto/providers/built_in/__init__.py
pdftools_sdk/crypto/providers/built_in/provider.py
pdftools_sdk/crypto/providers/built_in/signature_configuration.py
pdftools_sdk/crypto/providers/built_in/timestamp_configuration.py
pdftools_sdk/crypto/providers/global_sign_dss/__init__.py
pdftools_sdk/crypto/providers/global_sign_dss/session.py
pdftools_sdk/crypto/providers/global_sign_dss/signature_configuration.py
pdftools_sdk/crypto/providers/global_sign_dss/timestamp_configuration.py
pdftools_sdk/crypto/providers/pkcs11/__init__.py
pdftools_sdk/crypto/providers/pkcs11/device.py
pdftools_sdk/crypto/providers/pkcs11/device_list.py
pdftools_sdk/crypto/providers/pkcs11/module.py
pdftools_sdk/crypto/providers/pkcs11/session.py
pdftools_sdk/crypto/providers/pkcs11/signature_configuration.py
pdftools_sdk/crypto/providers/pkcs11/timestamp_configuration.py
pdftools_sdk-1.13.1.dist-info/METADATA
pdftools_sdk-1.13.1.dist-info/WHEEL
pdftools_sdk-1.13.1.dist-info/top_level.txt
pdftools_sdk-1.13.1.dist-info/RECORD
